{
  "family": "budgetbuddy-backend",
  "networkMode": "awsvpc",
  "requiresCompatibilities": ["FARGATE"],
  "cpu": "256",
  "memory": "512",
  "executionRoleArn": "arn:aws:iam::ACCOUNT_ID:role/ecsTaskExecutionRole",
  "taskRoleArn": "arn:aws:iam::ACCOUNT_ID:role/ecsTaskRole",
  "containerDefinitions": [
    {
      "name": "budgetbuddy-backend",
      "image": "ACCOUNT_ID.dkr.ecr.REGION.amazonaws.com/budgetbuddy-backend:latest",
      "essential": true,
      "portMappings": [
        {
          "containerPort": 8080,
          "protocol": "tcp"
        }
      ],
      "environment": [
        {
          "name": "AWS_REGION",
          "value": "us-east-1"
        },
        {
          "name": "DYNAMODB_TABLE_PREFIX",
          "value": "BudgetBuddy"
        },
        {
          "name": "AWS_CLOUDWATCH_ENABLED",
          "value": "true"
        },
        {
          "name": "AWS_CLOUDWATCH_LOG_GROUP",
          "value": "/aws/ecs/budgetbuddy-backend"
        }
      ],
      "secrets": [
        {
          "name": "JWT_SECRET",
          "valueFrom": "arn:aws:secretsmanager:REGION:ACCOUNT_ID:secret:budgetbuddy/jwt-secret"
        },
        {
          "name": "PLAID_CLIENT_ID",
          "valueFrom": "arn:aws:secretsmanager:REGION:ACCOUNT_ID:secret:budgetbuddy/plaid:clientId::"
        },
        {
          "name": "PLAID_SECRET",
          "valueFrom": "arn:aws:secretsmanager:REGION:ACCOUNT_ID:secret:budgetbuddy/plaid:secret::"
        }
      ],
      "logConfiguration": {
        "logDriver": "awslogs",
        "options": {
          "awslogs-group": "/aws/ecs/budgetbuddy-backend",
          "awslogs-region": "us-east-1",
          "awslogs-stream-prefix": "ecs"
        }
      },
      "healthCheck": {
        "command": [
          "CMD-SHELL",
          "wget --no-verbose --tries=1 --spider http://localhost:8080/actuator/health || exit 1"
        ],
        "interval": 30,
        "timeout": 5,
        "retries": 3,
        "startPeriod": 40
      }
    }
  ],
  "runtimePlatform": {
    "cpuArchitecture": "ARM64",
    "operatingSystemFamily": "LINUX"
  }
}

