{
    "Items": [
        {
            "accountName": {
                "S": "Plaid 401k"
            },
            "accountType": {
                "S": "investment"
            },
            "lastSyncedAt": {
                "S": "2025-12-14T05:50:38.737192508Z"
            },
            "active": {
                "BOOL": true
            },
            "accountNumber": {
                "S": "6666"
            },
            "updatedAtTimestamp": {
                "N": "1765691438"
            },
            "userId": {
                "S": "1d168f5d-4fb7-4426-a6c0-a00afeaa3ac2"
            },
            "plaidAccountId": {
                "S": "Jz5GMoKJkeIRVpKKyjgwCAnlgQe8JjIBNy5lg"
            },
            "accountId": {
                "S": "8a5b52ac-5005-31d2-8afd-0806f08176b2"
            },
            "createdAt": {
                "S": "2025-12-14T05:50:37.440354341Z"
            },
            "accountSubtype": {
                "S": "401k"
            },
            "balance": {
                "N": "23631.9805"
            },
            "institutionName": {
                "S": "ins_127989"
            },
            "currencyCode": {
                "S": "USD"
            },
            "updatedAt": {
                "S": "2025-12-14T05:50:38.737192508Z"
            }
        },
        {
            "accountName": {
                "S": "Plaid Student Loan"
            },
            "accountType": {
                "S": "loan"
            },
            "lastSyncedAt": {
                "S": "2025-12-14T05:50:38.737192508Z"
            },
            "active": {
                "BOOL": true
            },
            "accountNumber": {
                "S": "7777"
            },
            "updatedAtTimestamp": {
                "N": "1765691438"
            },
            "userId": {
                "S": "1d168f5d-4fb7-4426-a6c0-a00afeaa3ac2"
            },
            "plaidAccountId": {
                "S": "kaqe7grvw5CbrWPPvDl4SQXDj3pdaGsLRj84p"
            },
            "accountId": {
                "S": "f4f4e3ca-c364-30ee-8d4e-23435ea1cd1b"
            },
            "createdAt": {
                "S": "2025-12-14T05:50:37.455176758Z"
            },
            "accountSubtype": {
                "S": "student"
            },
            "balance": {
                "N": "65262"
            },
            "institutionName": {
                "S": "ins_127989"
            },
            "currencyCode": {
                "S": "USD"
            },
            "updatedAt": {
                "S": "2025-12-14T05:50:38.737192508Z"
            }
        },
        {
            "accountName": {
                "S": "Plaid Growth Cash Management"
            },
            "accountType": {
                "S": "depository"
            },
            "lastSyncedAt": {
                "S": "2025-12-14T05:50:38.737192508Z"
            },
            "active": {
                "BOOL": true
            },
            "accountNumber": {
                "S": "9002"
            },
            "updatedAtTimestamp": {
                "N": "1765691438"
            },
            "userId": {
                "S": "1d168f5d-4fb7-4426-a6c0-a00afeaa3ac2"
            },
            "plaidAccountId": {
                "S": "KB5e1grJRQsnPBggVbAdFygpAEq4z8iR39mlo"
            },
            "accountId": {
                "S": "cb84bca1-a65c-397b-90ba-e34b7030c13e"
            },
            "createdAt": {
                "S": "2025-12-14T05:50:37.491988550Z"
            },
            "accountSubtype": {
                "S": "cash management"
            },
            "balance": {
                "N": "12060"
            },
            "institutionName": {
                "S": "ins_127989"
            },
            "currencyCode": {
                "S": "USD"
            },
            "updatedAt": {
                "S": "2025-12-14T05:50:38.737192508Z"
            }
        },
        {
            "accountName": {
                "S": "Plaid Platinum Small Business Credit Card"
            },
            "accountType": {
                "S": "credit"
            },
            "lastSyncedAt": {
                "S": "2025-12-14T05:50:38.737192508Z"
            },
            "active": {
                "BOOL": true
            },
            "accountNumber": {
                "S": "9999"
            },
            "updatedAtTimestamp": {
                "N": "1765691438"
            },
            "userId": {
                "S": "1d168f5d-4fb7-4426-a6c0-a00afeaa3ac2"
            },
            "plaidAccountId": {
                "S": "rQdLpb4vqVhqlxRRVbA5ibKr5XdyMeu7BADr9"
            },
            "accountId": {
                "S": "024a08b1-b8b1-32d0-ab00-71f25e0b9be8"
            },
            "createdAt": {
                "S": "2025-12-14T05:50:37.511469300Z"
            },
            "accountSubtype": {
                "S": "credit card"
            },
            "balance": {
                "N": "4980"
            },
            "institutionName": {
                "S": "ins_127989"
            },
            "currencyCode": {
                "S": "USD"
            },
            "updatedAt": {
                "S": "2025-12-14T05:50:38.737192508Z"
            }
        },
        {
            "accountName": {
                "S": "Plaid Mortgage"
            },
            "accountType": {
                "S": "loan"
            },
            "lastSyncedAt": {
                "S": "2025-12-14T05:50:38.737192508Z"
            },
            "active": {
                "BOOL": true
            },
            "accountNumber": {
                "S": "8888"
            },
            "updatedAtTimestamp": {
                "N": "1765691438"
            },
            "userId": {
                "S": "1d168f5d-4fb7-4426-a6c0-a00afeaa3ac2"
            },
            "plaidAccountId": {
                "S": "l4KXe8z67VU5zjaa8wkntlWgZNLad5fpAqrKR"
            },
            "accountId": {
                "S": "160bd8c8-a86c-3bca-9bc7-ed1af0b85e43"
            },
            "createdAt": {
                "S": "2025-12-14T05:50:37.468204258Z"
            },
            "accountSubtype": {
                "S": "mortgage"
            },
            "balance": {
                "N": "56302.06"
            },
            "institutionName": {
                "S": "ins_127989"
            },
            "currencyCode": {
                "S": "USD"
            },
            "updatedAt": {
                "S": "2025-12-14T05:50:38.737192508Z"
            }
        },
        {
            "accountName": {
                "S": "Plaid Gold Standard 0% Interest Checking"
            },
            "accountType": {
                "S": "depository"
            },
            "lastSyncedAt": {
                "S": "2025-12-14T05:50:38.737192508Z"
            },
            "active": {
                "BOOL": true
            },
            "accountNumber": {
                "S": "0000"
            },
            "updatedAtTimestamp": {
                "N": "1765691438"
            },
            "userId": {
                "S": "1d168f5d-4fb7-4426-a6c0-a00afeaa3ac2"
            },
            "plaidAccountId": {
                "S": "6P8wRK1pXWhyjdEEawZ4fb1V6KBER7u8AlxEd"
            },
            "accountId": {
                "S": "261b8709-a41a-33cd-99de-b676b464855a"
            },
            "createdAt": {
                "S": "2025-12-14T05:50:37.356892008Z"
            },
            "accountSubtype": {
                "S": "checking"
            },
            "balance": {
                "N": "100"
            },
            "institutionName": {
                "S": "ins_127989"
            },
            "currencyCode": {
                "S": "USD"
            },
            "updatedAt": {
                "S": "2025-12-14T05:50:38.737192508Z"
            }
        },
        {
            "accountName": {
                "S": "Plaid Platinum Standard 1.85% Interest Money Market"
            },
            "accountType": {
                "S": "depository"
            },
            "lastSyncedAt": {
                "S": "2025-12-14T05:50:38.737192508Z"
            },
            "active": {
                "BOOL": true
            },
            "accountNumber": {
                "S": "4444"
            },
            "updatedAtTimestamp": {
                "N": "1765691438"
            },
            "userId": {
                "S": "1d168f5d-4fb7-4426-a6c0-a00afeaa3ac2"
            },
            "plaidAccountId": {
                "S": "wpjzWrev3VT6WrJJvdDzCKdkBaQmJbsPdpl4x"
            },
            "accountId": {
                "S": "6277f0a6-3e12-3075-b9ff-e271eee79b06"
            },
            "createdAt": {
                "S": "2025-12-14T05:50:37.415147716Z"
            },
            "accountSubtype": {
                "S": "money market"
            },
            "balance": {
                "N": "43200"
            },
            "institutionName": {
                "S": "ins_127989"
            },
            "currencyCode": {
                "S": "USD"
            },
            "updatedAt": {
                "S": "2025-12-14T05:50:38.737192508Z"
            }
        },
        {
            "accountName": {
                "S": "Plaid Cares Health Savings Account"
            },
            "accountType": {
                "S": "depository"
            },
            "lastSyncedAt": {
                "S": "2025-12-14T05:50:38.737192508Z"
            },
            "active": {
                "BOOL": true
            },
            "accountNumber": {
                "S": "9001"
            },
            "updatedAtTimestamp": {
                "N": "1765691438"
            },
            "userId": {
                "S": "1d168f5d-4fb7-4426-a6c0-a00afeaa3ac2"
            },
            "plaidAccountId": {
                "S": "qexmLnavlVcqQE55vD3Gie9Pa53XMzSgXjVey"
            },
            "accountId": {
                "S": "5b34a72e-c3c9-3dbd-b288-723ad2229612"
            },
            "createdAt": {
                "S": "2025-12-14T05:50:37.480005716Z"
            },
            "accountSubtype": {
                "S": "hsa"
            },
            "balance": {
                "N": "6009"
            },
            "institutionName": {
                "S": "ins_127989"
            },
            "currencyCode": {
                "S": "USD"
            },
            "updatedAt": {
                "S": "2025-12-14T05:50:38.737192508Z"
            }
        },
        {
            "accountName": {
                "S": "Plaid IRA"
            },
            "accountType": {
                "S": "investment"
            },
            "lastSyncedAt": {
                "S": "2025-12-14T05:50:38.737192508Z"
            },
            "active": {
                "BOOL": true
            },
            "accountNumber": {
                "S": "5555"
            },
            "updatedAtTimestamp": {
                "N": "1765691438"
            },
            "userId": {
                "S": "1d168f5d-4fb7-4426-a6c0-a00afeaa3ac2"
            },
            "plaidAccountId": {
                "S": "5Ngwvq1k7EU1a4DDd6WyCqn67jE9Ddt5LnpaM"
            },
            "accountId": {
                "S": "a59efe8d-d045-3c15-8d28-b5a84c9ac4a9"
            },
            "createdAt": {
                "S": "2025-12-14T05:50:37.426993966Z"
            },
            "accountSubtype": {
                "S": "ira"
            },
            "balance": {
                "N": "320.76"
            },
            "institutionName": {
                "S": "ins_127989"
            },
            "currencyCode": {
                "S": "USD"
            },
            "updatedAt": {
                "S": "2025-12-14T05:50:38.737192508Z"
            }
        },
        {
            "accountName": {
                "S": "Plaid Diamond 12.5% APR Interest Credit Card"
            },
            "accountType": {
                "S": "credit"
            },
            "lastSyncedAt": {
                "S": "2025-12-14T05:50:38.737192508Z"
            },
            "active": {
                "BOOL": true
            },
            "accountNumber": {
                "S": "3333"
            },
            "updatedAtTimestamp": {
                "N": "1765691438"
            },
            "userId": {
                "S": "1d168f5d-4fb7-4426-a6c0-a00afeaa3ac2"
            },
            "plaidAccountId": {
                "S": "VQ5XbK7BpAhNKRVVq4oBcX5p1q49VkF9AVnjw"
            },
            "accountId": {
                "S": "5316daea-e0b2-3cbc-a5a9-bdf834145332"
            },
            "createdAt": {
                "S": "2025-12-14T05:50:37.403164674Z"
            },
            "accountSubtype": {
                "S": "credit card"
            },
            "balance": {
                "N": "410"
            },
            "institutionName": {
                "S": "ins_127989"
            },
            "currencyCode": {
                "S": "USD"
            },
            "updatedAt": {
                "S": "2025-12-14T05:50:38.737192508Z"
            }
        },
        {
            "accountName": {
                "S": "Plaid Bronze Standard 0.2% Interest CD"
            },
            "accountType": {
                "S": "depository"
            },
            "lastSyncedAt": {
                "S": "2025-12-14T05:50:38.737192508Z"
            },
            "active": {
                "BOOL": true
            },
            "accountNumber": {
                "S": "2222"
            },
            "updatedAtTimestamp": {
                "N": "1765691438"
            },
            "userId": {
                "S": "1d168f5d-4fb7-4426-a6c0-a00afeaa3ac2"
            },
            "plaidAccountId": {
                "S": "DW5rPQ9Joaha86zz4pr1Fvk4JoZyPeu3poXAb"
            },
            "accountId": {
                "S": "29dfc440-025e-3479-b31c-b385c089a583"
            },
            "createdAt": {
                "S": "2025-12-14T05:50:37.391381049Z"
            },
            "accountSubtype": {
                "S": "cd"
            },
            "balance": {
                "N": "1000"
            },
            "institutionName": {
                "S": "ins_127989"
            },
            "currencyCode": {
                "S": "USD"
            },
            "updatedAt": {
                "S": "2025-12-14T05:50:38.737192508Z"
            }
        },
        {
            "accountName": {
                "S": "Plaid Silver Standard 0.1% Interest Saving"
            },
            "accountType": {
                "S": "depository"
            },
            "lastSyncedAt": {
                "S": "2025-12-14T05:50:38.737192508Z"
            },
            "active": {
                "BOOL": true
            },
            "accountNumber": {
                "S": "1111"
            },
            "updatedAtTimestamp": {
                "N": "1765691438"
            },
            "userId": {
                "S": "1d168f5d-4fb7-4426-a6c0-a00afeaa3ac2"
            },
            "plaidAccountId": {
                "S": "XM5NykDxonFKXpDDG6Ewi6RDy1xrXgCblXx7V"
            },
            "accountId": {
                "S": "07ff3651-5b7b-3280-8c29-93e6a52bb7a6"
            },
            "createdAt": {
                "S": "2025-12-14T05:50:37.377611258Z"
            },
            "accountSubtype": {
                "S": "savings"
            },
            "balance": {
                "N": "200"
            },
            "institutionName": {
                "S": "ins_127989"
            },
            "currencyCode": {
                "S": "USD"
            },
            "updatedAt": {
                "S": "2025-12-14T05:50:38.737192508Z"
            }
        }
    ],
    "Count": 12,
    "ScannedCount": 12,
    "ConsumedCapacity": null
}
